MANIFEST.in
setup.py
django_jquery_qtip.egg-info/PKG-INFO
django_jquery_qtip.egg-info/SOURCES.txt
django_jquery_qtip.egg-info/dependency_links.txt
django_jquery_qtip.egg-info/requires.txt
django_jquery_qtip.egg-info/top_level.txt
jquery_qtip/__init__.py
jquery_qtip/models.py
jquery_qtip/static/css/jquery.qtip.css
jquery_qtip/static/js/jquery.qtip.js