Metadata-Version: 1.1
Name: django-jquery-qtip
Version: 2.1.1
Summary: jQuery qTip (http://qtip2.com) packaged in a django app to speed up new applications and deployment.
Home-page: https://github.com/benbacardi/django-jquery-qtip
Author: Ben Cardy
Author-email: benbacardi@gmail.com
License: MIT
Keywords: django,jquery,qtip,staticfiles
Platform: any
Classifier: Development Status :: 5 - Production/Stable
Classifier: Environment :: Web Environment
Classifier: Framework :: Django
Classifier: Intended Audience :: Developers
Classifier: Natural Language :: English
Classifier: License :: OSI Approved :: MIT License
Classifier: Operating System :: OS Independent
Classifier: Programming Language :: Python
Classifier: Topic :: Utilities
